{
	"backtrace" : 1,
	"backtraceGraph" : 
	{
		"commands" : 
		[
			"add_custom_target"
		],
		"files" : 
		[
			"curl/CMakeLists.txt"
		],
		"nodes" : 
		[
			{
				"file" : 0
			},
			{
				"command" : 0,
				"file" : 0,
				"line" : 1665,
				"parent" : 0
			}
		]
	},
	"id" : "curl_uninstall::@108cb76c953c85671d68",
	"name" : "curl_uninstall",
	"paths" : 
	{
		"build" : "curl",
		"source" : "curl"
	},
	"sourceGroups" : 
	[
		{
			"name" : "",
			"sourceIndexes" : 
			[
				0
			]
		},
		{
			"name" : "CMake Rules",
			"sourceIndexes" : 
			[
				1
			]
		}
	],
	"sources" : 
	[
		{
			"backtrace" : 1,
			"isGenerated" : true,
			"path" : "build/curl/CMakeFiles/curl_uninstall",
			"sourceGroupIndex" : 0
		},
		{
			"backtrace" : 0,
			"isGenerated" : true,
			"path" : "build/curl/CMakeFiles/curl_uninstall.rule",
			"sourceGroupIndex" : 1
		}
	],
	"type" : "UTILITY"
}
